fastapi_app_ext/__init__.py
fastapi_app_ext/_app_ext.py
fastapi_app_ext/assets/css/swagger-ui.css
fastapi_app_ext/assets/js/redoc.standalone.js
fastapi_app_ext/assets/js/swagger-ui-bundle.js
fastapi_app_ext-0.1.5.dist-info/LICENSE
fastapi_app_ext-0.1.5.dist-info/METADATA
fastapi_app_ext-0.1.5.dist-info/WHEEL
fastapi_app_ext-0.1.5.dist-info/top_level.txt
fastapi_app_ext-0.1.5.dist-info/RECORD
