Metadata-Version: 2.1
Name: fastapi-app-ext
Version: 0.1.5
Summary: The extended function library of fastapi can be read README.md
Home-page: https://github.com/hgz1989/fastapi-app-ext
Author: HanGuangZheng
Author-email: hanguangzheng@qq.com
Classifier: Programming Language :: Python :: 3
Classifier: License :: OSI Approved :: MIT License
Classifier: Operating System :: OS Independent
Requires-Python: >=3.8
License-File: LICENSE
Requires-Dist: fastapi>=0.114.0
